{
    "success": true,
    "title": "什么值得买",
    "subtitle": "好价排行榜",
    "update_time": "2024-05-24 17:57:24",
    "data": [
        {
            "index": 1,
            "url": "https://www.smzdm.com/p/113602664/",
            "title": "Mr.Seafood 京鲜生 海南妃子笑荔枝 净重1kg/当季鲜橙 净重3kg（每斤荔枝9.1元、橙子3元，油桃、香蕉等）",
            "price": "18.57元"
        },
        {
            "index": 2,
            "url": "https://www.smzdm.com/p/113597924/",
            "title": "会员优享：UE 永艺 撑腰椅XY椅人体工学椅 竞速骑士-无搁脚",
            "price": "390.21元（需用券）"
        },
        {
            "index": 3,
            "url": "https://www.smzdm.com/p/113614354/",
            "title": "百亿补贴：乡寸 海南金煌芒果5斤装 单果350g起",
            "price": "16.9元（多人团）"
        },
        {
            "index": 4,
            "url": "https://www.smzdm.com/p/113623237/",
            "title": "88VIP：心相印 茶语经典系列 抽纸 3层*110抽*30包(190*132mm)",
            "price": "33.91元（需用券）"
        },
        {
            "index": 5,
            "url": "https://www.smzdm.com/p/113545804/",
            "title": "Mr.Seafood 京鲜生 国产黄肉油桃 净重2.5kg 单果60g以上",
            "price": "14.9元"
        },
        {
            "index": 6,
            "url": "https://www.smzdm.com/p/113358580/",
            "title": "PLUS会员：Kerchin 科尔沁 手撕风干牛肉干 原味618g",
            "price": "91.2元"
        },
        {
            "index": 7,
            "url": "https://www.smzdm.com/p/113479603/",
            "title": "Goodfarmer 佳农 烟台红富士苹果 净重5kg装",
            "price": "49.95元"
        },
        {
            "index": 8,
            "url": "https://www.smzdm.com/p/113619718/",
            "title": "Bananain 蕉内 男士平角莫代尔抗菌内裤 3P-BU311S-P 3件装",
            "price": "59.33元（需用券）"
        },
        {
            "index": 9,
            "url": "https://www.smzdm.com/p/113612376/",
            "title": "JOMOO 九牧 A2721-15LD-1 极简浴室柜组合 珍珠白 80cm",
            "price": "765.15元（需用券）"
        },
        {
            "index": 10,
            "url": "https://www.smzdm.com/p/113634273/",
            "title": "Mizuno 美津浓 24男女运动鞋稳定支撑透气鞋面耐磨跑步鞋子WAVE INSPIRE 20",
            "price": "279.42元（需用券）"
        },
        {
            "index": 11,
            "url": "https://www.smzdm.com/p/113020723/",
            "title": "概率券：京东 粉丝福利 可领0.2-188元随机红包",
            "price": "实测0.6元无门槛红包"
        },
        {
            "index": 12,
            "url": "https://www.smzdm.com/p/113637865/",
            "title": "WAHIN 华凌 空调家用卧室挂机冷暖大1.5匹一级变频35HL1Pro",
            "price": "1429元（需用券）"
        },
        {
            "index": 13,
            "url": "https://www.smzdm.com/p/113554762/",
            "title": "20点开始：泰坦军团 P24A2GC 23.8英寸Fast IPS显示器（1920*1080、180Hz、1ms、 HDR10、132%sRGB）",
            "price": "289元（晒单返10元E卡后）"
        },
        {
            "index": 14,
            "url": "https://www.smzdm.com/p/112964131/",
            "title": "Epic Games 喜加一 《模拟农场22》PC数字版游戏",
            "price": "0元限时免费领取"
        },
        {
            "index": 15,
            "url": "https://www.smzdm.com/p/113492852/",
            "title": "Zespri 佳沛 新西兰阳光金奇异果 巨大果10粒礼盒（单果146-175g）（买1赠1，还有苹果、牛油果等）",
            "price": "72.95元（需买2件，需用券）"
        },
        {
            "index": 16,
            "url": "https://www.smzdm.com/p/113119035/",
            "title": "nulo诺乐两款热销猫粮真实测评，该选自由天性还是金牌系列呢？",
            "price": "618活动进行中，下单超省，不要再犹豫了~"
        },
        {
            "index": 17,
            "url": "https://www.smzdm.com/p/113668764/",
            "title": "ASICS 亚瑟士 GEL-CONTEND 4 男子跑鞋 T8D4Q-029 灰色/蓝色 42.5",
            "price": "240.47元（需用券）"
        },
        {
            "index": 18,
            "url": "https://www.smzdm.com/p/113479486/",
            "title": "Mr.Seafood 京鲜生 泰国进口金枕头榴莲 2-4个装 总重7kg以上 新鲜水果",
            "price": "320.02元"
        },
        {
            "index": 19,
            "url": "https://www.smzdm.com/p/113607410/",
            "title": "25日0点：京东云 无线宝 AX6600 雅典娜 128G 三频6600M 家用千兆Mesh无线路由器 Wi-Fi 6 单个装 黑色",
            "price": "434元（需首购礼金）"
        },
        {
            "index": 20,
            "url": "https://www.smzdm.com/p/113626055/",
            "title": "运动凑单购：Mizuno 美津浓 WAVE RIDER 27 男女款运动慢跑鞋 J1GC230305",
            "price": "385.77元包邮（需凑单，实付共551.8元）"
        },
        {
            "index": 21,
            "url": "https://www.smzdm.com/p/113620520/",
            "title": "百亿补贴：Apple 苹果 iPhone 15 Pro 5G手机 256GB",
            "price": "6695元（需用券、叠加多多支付可更低~）"
        },
        {
            "index": 22,
            "url": "https://www.smzdm.com/p/113471539/",
            "title": "整点领：京东金融 消费日历 领4元白条购物券",
            "price": "领2元白条购物券"
        },
        {
            "index": 23,
            "url": "https://www.smzdm.com/p/113634028/",
            "title": "PLUS会员：Mizuno 美津浓 WAVE SKY 7  男子运动跑步鞋 J1GC230252",
            "price": "419.7元（需凑单，共553.24元）"
        },
        {
            "index": 24,
            "url": "https://www.smzdm.com/p/113631368/",
            "title": "88VIP：SENSODYNE 舒适达 专业修复牙膏 100g",
            "price": "23.1元（需用券）"
        },
        {
            "index": 25,
            "url": "https://www.smzdm.com/p/113629089/",
            "title": "淘宝88VIP免费开盲盒，新开会员可中10元天猫超市卡",
            "price": "限时奖品加码，额外加赠10元天猫超市卡"
        },
        {
            "index": 26,
            "url": "https://www.smzdm.com/p/113616015/",
            "title": "任务券：5.24 招行活动合集 完成任务抽现金红包",
            "price": "领随机现金红包"
        },
        {
            "index": 27,
            "url": "https://www.smzdm.com/p/113533138/",
            "title": "百人团、评论有奖：瑷尔博士送福利！碎银、金币轻松领！",
            "price": "摇醒精华Pro，温和焕亮熬夜肌！"
        },
        {
            "index": 28,
            "url": "https://www.smzdm.com/p/113633340/",
            "title": "SATINE 金典 伊利金典纯牛奶250ml*16盒/箱 3.6g乳蛋白 早餐伴侣",
            "price": "36.9元（需买2件，需用券）"
        },
        {
            "index": 29,
            "url": "https://www.smzdm.com/p/113307356/",
            "title": "大件超省、88VIP：MENGSHEN 梦神 熊猫滚滚8H 3D弹韧黄麻护脊床垫 1.8/1.5m*2m",
            "price": "999元包邮（双重优惠）"
        },
        {
            "index": 30,
            "url": "https://www.smzdm.com/p/113323081/",
            "title": "评论有奖、百人团：雅迪618热门爆款抢先购 ",
            "price": "前100位抢至高450元京东E卡"
        }
    ]
}